{"Epoch": {"data": [{"name": "Epoch", "x": [0], "y": [0]}], "layout": {"title": "Epoch"}}, "LR": {"data": [{"name": "LR", "x": [0], "y": [0]}], "layout": {"title": "LR"}}, "loss": {"data": [{"name": "train", "x": [0], "y": [5.545971201504356]}, {"name": "val", "x": [0], "y": [5.545971201504356]}], "layout": {"title": "loss"}}, "perf0": {"data": [{"name": "train", "x": [0], "y": [0.04881522724329924]}, {"name": "val", "x": [0], "y": [0.04881522724329924]}], "layout": {"title": "perf0"}}, "perf1": {"data": [{"name": "train", "x": [0], "y": [0.12132590962061375]}, {"name": "val", "x": [0], "y": [0.12132590962061375]}], "layout": {"title": "perf1"}}}